bmkg_data/__init__.py
bmkg_data/earthquake.py
bmkg_data-0.1.0.dist-info/LICENSE
bmkg_data-0.1.0.dist-info/METADATA
bmkg_data-0.1.0.dist-info/WHEEL
bmkg_data-0.1.0.dist-info/top_level.txt
bmkg_data-0.1.0.dist-info/RECORD
